curricula_format/__init__.py
curricula_format/shell.py
curricula_format/version.py
curricula_format/template/report/assignment.md
curricula_format/template/report/problem.md
curricula_format-2.1.3.dist-info/LICENSE
curricula_format-2.1.3.dist-info/METADATA
curricula_format-2.1.3.dist-info/WHEEL
curricula_format-2.1.3.dist-info/top_level.txt
curricula_format-2.1.3.dist-info/RECORD
