Metadata-Version: 2.1
Name: curricula-format
Version: 2.1.3
Summary: A markdown formatter for reports generated by curricula_grade
Home-page: https://github.com/curriculagg/curricula-format
Author: Noah Kim
Author-email: noahbkim@gmail.com
License: UNKNOWN
Platform: UNKNOWN
Requires-Python: >=3.9
Requires-Dist: curricula (~=2.1)
Requires-Dist: curricula-grade (~=2.1)
